<?xml version="1.0"?>
<Parameters>
  <Parameter id="systemsettings" value="eBoolean:true" />
  <Parameter id="xmlfiles" value="eString:Partner\\publicationstatisticalreport.xml" />
  <Parameter id="currentReport" value="eString:Publication Statistical Report" />
  <Parameter id="MaxDisplayColumns" value="eInteger:5" />
  <Parameter id="param_calculation" column="0" value="eString:County" />
  <Parameter id="ColumnWidth" column="0" value="eInteger:3" />
  <Parameter id="param_calculation" column="1" value="eString:Donors" />
  <Parameter id="ColumnWidth" column="1" value="eDecimal:1.3" />
  <Parameter id="param_calculation" column="2" value="eString:ExParticipants" />
  <Parameter id="ColumnWidth" column="2" value="eDecimal:2.3" />
  <Parameter id="param_calculation" column="3" value="eString:Churches" />
  <Parameter id="ColumnWidth" column="3" value="eDecimal:1.7" />
  <Parameter id="param_calculation" column="4" value="eString:Applicants" />
  <Parameter id="ColumnWidth" column="4" value="eDecimal:1.8" />
  <Parameter id="param_subscriptionoptions" value="eString:AllSubscriptions" />
</Parameters>