<?xml version="1.0"?>
<Parameters>
  <Parameter id="systemsettings" value="True" />
  <Parameter id="xmlfiles" value="Conference\\outreachreport.xml,Conference\\conference.xml" />
  <Parameter id="currentReport" value="Outreach Report" />
  <Parameter id="MaxDisplayColumns" value="14" />
  <Parameter id="param_conferenceselection" value="one conference" />
  <Parameter id="param_attendeeselection" value="all attendees" />
  <Parameter id="param_partnerkey" value="0" />
  <Parameter id="param_conferencekey" value="0" />
  <Parameter id="param_conferencename" value="" />
  <Parameter id="param_extractname" value="" />
  <Parameter id="param_calculation" column="14" value="DummyValue14" />
  <Parameter id="param_report_detail" value="Full" />
  <Parameter id="param_selected_keys_csv" value="" />
  <Parameter id="param_chkFinancialReport" value="true" />
  <Parameter id="param_chkAcceptedApplications" value="false" />
  <Parameter id="param_chkExtraCosts" value="false" />
  <Parameter id="param_cmbSignOffLines" value="no Sign Off Lines" />
  <Parameter id="param_cmbChargedFields" value="leave data as it is" />
  <Parameter id="param_calculation" column="0" value="Partner Name" />
  <Parameter id="ColumnWidth" column="0" value="3.5" />
  <Parameter id="param_calculation" column="1" value="Gender" />
  <Parameter id="ColumnWidth" column="1" value="1.2" />
  <Parameter id="param_calculation" column="2" value="Marital Status" />
  <Parameter id="ColumnWidth" column="2" value="1" />
  <Parameter id="param_calculation" column="3" value="Passport Number" />
  <Parameter id="ColumnWidth" column="3" value="3" />
  <Parameter id="param_calculation" column="4" value="Age" />
  <Parameter id="ColumnWidth" column="4" value="0.8" />
  <Parameter id="param_calculation" column="5" value="Arrival Date" />
  <Parameter id="ColumnWidth" column="5" value="1.8" />
  <Parameter id="param_calculation" column="6" value="Departure Date" />
  <Parameter id="ColumnWidth" column="6" value="1.8" />
  <Parameter id="param_calculation" column="7" value="Conference Role" />
  <Parameter id="ColumnWidth" column="7" value="1.5" />
  <Parameter id="param_calculation" column="8" value="Application Status" />
  <Parameter id="ColumnWidth" column="8" value="1" />
  <Parameter id="param_calculation" column="9" value="Outreach Code" />
  <Parameter id="ColumnWidth" column="9" value="3" />
  <Parameter id="param_calculation" column="10" value="Fellowship Group" />
  <Parameter id="ColumnWidth" column="10" value="1.5" />
  <Parameter id="param_calculation" column="11" value="Driver Status" />
  <Parameter id="ColumnWidth" column="11" value="2" />
  <Parameter id="param_calculation" column="12" value="Missing Information" />
  <Parameter id="ColumnWidth" column="12" value="3.2" />
  <Parameter id="param_calculation" column="13" value="Finance Details" />
  <Parameter id="ColumnWidth" column="13" value="3" />
</Parameters>